vot2fits.py
vot2fits-0.1.0.dist-info/LICENSE
vot2fits-0.1.0.dist-info/METADATA
vot2fits-0.1.0.dist-info/WHEEL
vot2fits-0.1.0.dist-info/entry_points.txt
vot2fits-0.1.0.dist-info/RECORD
